jobsbundle/JobsBundle.py
jobsbundle/JobsBundleTest.py
jobsbundle/_config/.gitignore
jobsbundle/_config/config.yaml
jobsbundle/_config/config_test.yaml
jobsbundle/job/AllJobsCreatorCommand.py
jobsbundle/job/JobCreateOrUpdateCommand.py
jobsbundle/job/JobCreatorCommand.py
jobsbundle/job/JobIdFinder.py
jobsbundle/job/Router.py
jobsbundle/job/StreamingJobCreateCommand.py
jobsbundle/job/StreamingJobCreateOrUpdateCommand.py
jobsbundle/job/ValuesFiller.py
jobsbundle/job/argparser_configurator.py
jobsbundle/job/template_filler.py
jobs_bundle-0.5.2.dist-info/entry_points.txt
jobs_bundle-0.5.2.dist-info/LICENSE
jobs_bundle-0.5.2.dist-info/WHEEL
jobs_bundle-0.5.2.dist-info/METADATA
jobs_bundle-0.5.2.dist-info/RECORD
